<annotation>
	<folder>test</folder>
	<filename>frame0337.jpg</filename>
	<path>/home/jobvakayil/test/frame0337.jpg</path>
	<source>
		<database>Unknown</database>
	</source>
	<size>
		<width>800</width>
		<height>600</height>
		<depth>3</depth>
	</size>
	<segmented>0</segmented>
	<object>
		<name>GREEN</name>
		<pose>Unspecified</pose>
		<truncated>0</truncated>
		<difficult>0</difficult>
		<bndbox>
			<xmin>6</xmin>
			<ymin>510</ymin>
			<xmax>28</xmax>
			<ymax>555</ymax>
		</bndbox>
	</object>
	<object>
		<name>GREEN</name>
		<pose>Unspecified</pose>
		<truncated>0</truncated>
		<difficult>0</difficult>
		<bndbox>
			<xmin>73</xmin>
			<ymin>513</ymin>
			<xmax>95</xmax>
			<ymax>560</ymax>
		</bndbox>
	</object>
	<object>
		<name>GREEN</name>
		<pose>Unspecified</pose>
		<truncated>0</truncated>
		<difficult>0</difficult>
		<bndbox>
			<xmin>137</xmin>
			<ymin>515</ymin>
			<xmax>158</xmax>
			<ymax>558</ymax>
		</bndbox>
	</object>
</annotation>
