<annotation>
	<folder>test</folder>
	<filename>frame0325.jpg</filename>
	<path>/home/jobvakayil/test/frame0325.jpg</path>
	<source>
		<database>Unknown</database>
	</source>
	<size>
		<width>800</width>
		<height>600</height>
		<depth>3</depth>
	</size>
	<segmented>0</segmented>
	<object>
		<name>GREEN</name>
		<pose>Unspecified</pose>
		<truncated>0</truncated>
		<difficult>0</difficult>
		<bndbox>
			<xmin>45</xmin>
			<ymin>536</ymin>
			<xmax>63</xmax>
			<ymax>574</ymax>
		</bndbox>
	</object>
	<object>
		<name>GREEN</name>
		<pose>Unspecified</pose>
		<truncated>0</truncated>
		<difficult>0</difficult>
		<bndbox>
			<xmin>95</xmin>
			<ymin>541</ymin>
			<xmax>110</xmax>
			<ymax>573</ymax>
		</bndbox>
	</object>
</annotation>
